Metadata-Version: 1.1
Name: macCC
Version: 0.0.1
Summary: A tool to capture Mac clipboard image
Home-page: http://cijianzy.com
Author: cijianzy
Author-email: cijianzy@gmail.com
License: UNKNOWN
Platform: UNKNOWN
Classifier: Programming Language :: Python
Classifier: License :: OSI Approved :: MIT License
Classifier: Development Status :: 3 - Alpha
